LICENSE
MANIFEST.in
README.rst
development.ini
setup.py
data/GeoLiteCity.dat
narcissus/__init__.py
narcissus.hub.egg-info/PKG-INFO
narcissus.hub.egg-info/SOURCES.txt
narcissus.hub.egg-info/dependency_links.txt
narcissus.hub.egg-info/entry_points.txt
narcissus.hub.egg-info/namespace_packages.txt
narcissus.hub.egg-info/requires.txt
narcissus.hub.egg-info/top_level.txt
narcissus/hub/__init__.py
narcissus/hub/consumers.py
narcissus/hub/producers.py