Metadata-Version: 1.1
Name: narcissus.hub
Version: 0.9.0.1
Summary: Hub components for Narcissus, realtime log visualization
Home-page: http://narcissus.ws/
Author: Ralph Bean
Author-email: rbean@redhat.com
License: AGPLv3+
Platform: UNKNOWN
Classifier: License :: OSI Approved :: GNU Affero General Public License v3 or later (AGPLv3+)
Classifier: Topic :: Scientific/Engineering :: Visualization
Classifier: Topic :: System :: Logging
Classifier: Topic :: System :: Monitoring
Classifier: Intended Audience :: System Administrators
Classifier: Programming Language :: Python :: 2
Classifier: Programming Language :: Python :: 2.6
Classifier: Programming Language :: Python :: 2.7
